odoo/addons/stock_customer_deposit/README.rst
odoo/addons/stock_customer_deposit/__init__.py
odoo/addons/stock_customer_deposit/__manifest__.py
odoo/addons/stock_customer_deposit/i18n/es.po
odoo/addons/stock_customer_deposit/i18n/it.po
odoo/addons/stock_customer_deposit/i18n/stock_customer_deposit.pot
odoo/addons/stock_customer_deposit/models/__init__.py
odoo/addons/stock_customer_deposit/models/product.py
odoo/addons/stock_customer_deposit/models/res_partner.py
odoo/addons/stock_customer_deposit/models/sale_order.py
odoo/addons/stock_customer_deposit/models/sale_order_line.py
odoo/addons/stock_customer_deposit/models/stock_move.py
odoo/addons/stock_customer_deposit/models/stock_picking.py
odoo/addons/stock_customer_deposit/models/stock_picking_type.py
odoo/addons/stock_customer_deposit/models/stock_quant.py
odoo/addons/stock_customer_deposit/models/stock_rule.py
odoo/addons/stock_customer_deposit/models/stock_warehouse.py
odoo/addons/stock_customer_deposit/readme/CONFIGURE.md
odoo/addons/stock_customer_deposit/readme/CONTEXT.md
odoo/addons/stock_customer_deposit/readme/CONTRIBUTORS.md
odoo/addons/stock_customer_deposit/readme/DESCRIPTION.md
odoo/addons/stock_customer_deposit/readme/ROADMAP.md
odoo/addons/stock_customer_deposit/readme/USAGE.md
odoo/addons/stock_customer_deposit/static/description/icon.png
odoo/addons/stock_customer_deposit/static/description/index.html
odoo/addons/stock_customer_deposit/tests/__init__.py
odoo/addons/stock_customer_deposit/tests/common.py
odoo/addons/stock_customer_deposit/tests/test_deliver_customer_deposit.py
odoo/addons/stock_customer_deposit/tests/test_sale_customer_deposit.py
odoo/addons/stock_customer_deposit/tests/test_stock_warehouse.py
odoo/addons/stock_customer_deposit/views/res_partner_views.xml
odoo/addons/stock_customer_deposit/views/sale_order_views.xml
odoo/addons/stock_customer_deposit/views/stock_picking_type_views.xml
odoo/addons/stock_customer_deposit/views/stock_warehouse_views.xml
odoo_addon_stock_customer_deposit-16.0.1.2.1.dist-info/METADATA
odoo_addon_stock_customer_deposit-16.0.1.2.1.dist-info/WHEEL
odoo_addon_stock_customer_deposit-16.0.1.2.1.dist-info/top_level.txt
odoo_addon_stock_customer_deposit-16.0.1.2.1.dist-info/RECORD
